{
    "Accounting":{
        "#accountantandartist": 3121,
        "#accountantsarecool": 3037,
        "#accountantouting": 3017,
        "#accountantsrock": 2986,
        "#accountantshavefuntoo": 2803,
        "#smallbusinessaccountant": 2322,
        "#accountanthumor": 2251,
        "#accountingservice": 4426,
        "#softwareaccounting": 3959,
        "#accountingstaff": 3604,
        "#taxaccounting": 3439,
        "#accountingdept": 3284
    },
    "Airbnb":{
        "#airbnbmanagement": 14228,
        "#airbnb": 4708969,
        "#airbnbopen": 13648,
        "#airbnbcoupon": 12043,
        "#airbnbpartner": 11999,
        "#airbnbsuperhosts": 11982
    },
    "Art":{
        "#modernart": 16258864,
        "#urbanart": 14492932,
        "#artists": 13966646
    },
    "Bakery":{
        "#bakeryhouse": 67501,
        "#bestbakery": 56359,
        "#citybakery": 51494,
        "#healthybakery": 49460,
        "#bakeryrd": 49284
    },
    "Book Store":{
        "#scrapbook": 2844657,
        "#comicbook": 2789484,
        "#bookporn": 2615424,
        "#booking": 2481861,
        "#bookclub": 2473640,
        "#ilovebooks": 2439687,
        "#ebook": 2435436,
        "#childrensbooks": 2366136
    },
    "Breeding":{
        "#breedingstock": 5501,
        "#responsiblebreeding": 5078,
        "#inbreeding": 4834
    },
    "Brewery":{
        "#thebrewery": 23912,
        "#craftbeergeek": 868390,
        "#beeradvocate": 784262,
        "#goodbeer": 753247,
        "#lovebeer": 741044,
        "#beergram": 736831,
        "#craftbeers": 702796,
        "#beertasting": 690708,
        "#localbeer": 687489,
        "#beeroclock": 680836
    },
    "Cafe":{
        "#coffeeislife": 1200365,
        "#lovecoffee": 1149580,
        "#coffeebeans": 1126065,
        "#coffeesesh": 1089471,
        "#coffeeshots": 1088582,
        "#coffee_inst": 999419,
        "#manmakecoffee": 981871,
        "#coffeeroaster": 969093,
        "#coffeegeek": 954144,
        "#coffeebar": 938344
    },
    "Car Rentals":{
        "#instacars": 7629518,
        "#racecar": 7487638,
        "#cargram": 6622748
    },
    "Car Repairs":{
        "#carrepair":1
    },
    "Casino":{
        "#casinofun": 44029,
        "#casinoroyal": 27656
    },
    "Chinese Cuisine":{
        "#loveforchinesefood": 2865,
        "#yummychinesefood": 2514,
        "#chinesefooddelivery": 2398,
        "#chinesefoodfestival": 2377,
        "#instachinesefood": 2355,
        "#chinesefoodlove": 2311
    },
    "Chiropractor":{
        "#chiropractor":1
    },
    "Church":{
        "#stylegoestochurch": 152279,
        "#churchesofinstagram": 150877,
        "#mychurch": 140397
    },
    "Civil Engineering":{
        "#civilengineering": 65204,
        "#civilwork": 62113
    },
    "Coffee Shop":{
        "#coffeeislife": 1200365,
        "#lovecoffee": 1149580,
        "#coffeebeans": 1126065,
        "#coffeesesh": 1089471,
        "#coffeeshots": 1088582,
        "#coffee_inst": 999419,
        "#manmakecoffee": 981871,
        "#coffeeroaster": 969093,
        "#coffeegeek": 954144,
        "#coffeebar": 938344
    },
    "Computer Repairs":{
        "#personalcomputer": 23904,
        "#newcomputer": 23644,
        "#computertech": 22992,
        "#computerlab": 22822,
        "#computerproblems": 22185
    },
    "Concert":{
        "#summerconcert": 112688,
        "#concertnight": 109138
    },
    "Dentistry":{
        "#dentistoffice": 90101,
        "#instadentist": 88458,
        "#kidsdentist": 78821,
        "#dentisttime": 67051,
        "#dentistappointment": 66856,
        "#dentistday": 66706,
        "#generaldentistry": 62350,
        "#dentistvisit": 57483
    },
    "Diner":{
        "#dining": 3853349,
        "#diningexperience": 53773,
        "#diningarea": 51736,
        "#familyrestaurant": 170535,
        "#foodphoto": 7820982,
        "#foodlove": 7773452,
        "#igfood": 7771560,
        "#foodiegram": 7433680,
        "#comfortfood": 7127447,
        "#instafoodie": 6956649,
        "#foodoftheday": 6744279
    },
    "Education":{
        "#educationispower": 134731,
        "#healtheducation": 111082,
        "#earlyyearseducation": 103079
    },
    "Electrical Engineering":{
        "#electricalrepair": 79557,
        "#electricalservice": 7909
    },
    "Equipment Rental":{
        "#equipmentrental": 35807,
        "#pilatesequipment": 33323,
        "#earthmovingequipment": 29899
    },
    "Farm Stand":{
        "#farmtofork": 390693,
        "#farmhouseliving": 356858,
        "#farm365": 350329,
        "#organicfarm": 326298
    },
    "Fashion":{
        "#highfashion": 8383034,
        "#plussizefashion": 8302743,
        "#hairfashion": 8144926,
        "#vintagefashion": 7778666,
        "#fallfashion": 7430613,
        "#fashiongirl": 7294851,
        "#fashionstylist": 7210601,
        "#fashionjewelry": 7017288,
        "#fashionistas": 6751582
    },
    "Fast Food":{
        "#burger": 16622371,
        "#delicious": 109745418,
        "#fastfood": 4575487,
        "#fastfoodporn": 141197,
        "#foodie": 151598176,
        "#foodphotography": 54357884,
        "#foodporn": 993260,
        "#foodstagram": 67767315,
        "#instafood": 169891658,
        "#yummy": 15344390
    },
    "Financial Advising":{
        "#financialsupport": 40215,
        "#financialplan": 38339,
        "#financially": 37498,
        "#financials": 36468,
        "#financialempowerment": 34684,
        "#financialcoaching": 33825,
        "#financialadvisors": 33813,
        "#financiallyfit": 32050,
        "#financialtechnologi": 31792
    },
    "Fine Dining":{
        "#finefood": 371917,
        "#diningexperience": 53773,
        "#waterfrontdining": 53042,
        "#diningarea": 51736
    },
    "Fishing":{
        "#offshorefishing": 445625,
        "#deepseafishing": 424286,
        "#fishinggear": 420842,
        "#flyfishingnation": 411279,
        "#instafishing": 389231,
        "#salmonfishing": 334448
    },
    "Garden Center":{
        "#favv_flowers": 1009332,
        "#bestflowerspics": 1002405,
        "#yellowflowers": 902552,
        "#flowers_super_pics": 848359,
        "#flowersoftheday": 840752,
        "#instagardenlovers": 846405,
        "#backyardgarden": 824105,
        "#macrogardener": 765818,
        "#kitchengarden": 735308,
        "#gardensofinstagram": 692565
    },
    "Healthcare":{
        "#healthcareheros": 16256,
        "#healthcaretips": 15054,
        "#healthcarelife": 14278,
        "#babyhealthcare": 13689,
        "#supporthealthcareworkers": 132628,
        "#healthcareproviders": 123489,
        "#healthcare": 11002
    },
    "Health Food":{
        "#healthfoodlover": 1325,
        "#healthfoodrestaurant": 1243,
        "#lovehealthfood": 1131,
        "#healthfoodedition": 1128,
        "#healthfoodcentral": 1119,
        "#healthfoodaddict": 1055,
        "#healthfoodlab": 1045,
        "#healthfoodspa": 1019
    },
    "Historical Site":{
        "#historicalhomes": 23750,
        "#historicalpark": 20726,
        "#historicaltown": 20189,
        "#historicalfacts": 16589,
        "#historicalmuseum": 15756,
        "#historicalhome": 15602,
        "#historicalsociety": 15426,
        "#historicalphotography": 14381,
        "#historicalchurch": 14238
    },
    "Investing":{
        "#investorsclub": 15582,
        "#investorspecial": 14254,
        "#womeninvestors": 13317,
        "#investorsbusinessdaily": 13159,
        "#strictlyinvestor": 12549,
        "#noteinvestors": 12056,
        "#intelligentinvestor": 11919,
        "#cryptoinvestors": 10443
    },
    "Ice Cream Shop":{
        "#strawberryicecream": 124431,
        "#bananaicecream": 122265,
        "#icecreamofinsta": 120083,
        "#besticecream": 113313,
        "#icecreamdate": 106830,
        "#icecreamman": 106066,
        "#icecreamday": 101815,
        "#icecreamparty": 101709
    },
    "Japanese Cuisine":{
        "#japanesenoodle": 209050,
        "#japanesefoodstreet": 2516,
        "#japanesefoodislove": 2411,
        "#japanesefoodphoto": 2157,
        "#japanesefoodpic": 2136,
        "#yummyjapanesefood": 2122
    },
    "Landscaping":{
        "#backyardlandscaping": 4206,
        "#greenlawn": 33550,
        "#interiorlandscaping": 3656,
        "#landscapingbusiness": 3164,
        "#landscapingequipment": 3545,
        "#lawnmowers": 27918,
        "#lawnporn": 33250,
        "#mulchbed": 1200,
        "#softlandscaping": 3896,
        "#thelawn": 27714
    },
    "Manufacturing":{
        "#smartmanufacturing": 4701,
        "#fashionmanufacturing": 4050,
        "#manufacturingindustry": 4041,
        "#usamanufacturing": 3712,
        "#remanufacturing": 3391
    },
    "Marketing Agency":{
        "#marketingplan": 402808,
        "#webmarketing": 398636,
        "#marketingsocial": 365471,
        "#networkmarketingpro": 360991,
        "#marketingestrategico": 353461,
        "#facebookmarketing": 352082,
        "#smallbusinessmarketing": 341024,
        "#marketinglife": 333097,
        "#businessmarketing": 327142,
        "#mobilemarketing": 324399
    },
    "Masonry":{
        "#comasonry": 946,
        "#masonrysupply": 853,
        "#masonrytools": 664,
        "#stonemasonryart": 660,
        "#masonrycleaning": 659
    },
    "Mechanical Engineering":{
        "#mechanicalcontractor": 1099510,
        "#mechanical_engineer": 9914
    },
    "Mexican Cuisine":{
        "#goodmexicanfood": 2692,
        "#mexicanfoodisthebestfood": 2672,
        "#mexicanfoodstagram": 2473,
        "#freshmexicanfood": 2467,
        "#yummymexicanfood": 2345,
        "#mexicanfoodaddict": 2261,
        "#mexicanfoodfordays": 2229,
        "#greatmexicanfood": 2219,
        "#mexicanfoodrecipes": 2097,
        "#lovemesomemexicanfood": 2094
    },
    "News":{
        "#nflnews": 607701,
        "#footballnews": 593887,
        "#sportsnews": 583671,
        "#nbanews": 525128,
        "#boxingnews": 509959,
        "#entertainmentnews": 509217,
        "#newsletter": 469263,
        "#newshop": 464912,
        "#newstore": 445777
    },
    "Office Support Services":{
        "#officegoals": 237816,
        "#officetime": 213228,
        "#officesupplies": 206082,
        "#officefun": 205730,
        "#shoutoutoffice": 190675,
        "#officefashion": 188388,
        "#officeinterior": 179618,
        "#todaysoffice": 163326,
        "#officeoftheday": 157781
    },
    "Painting":{
        "#artpainting": 521826,
        "#modernpainting": 488249,
        "#figurepainting": 487044,
        "#paintingminiatures": 469237,
        "#livepainting": 451410,
        "#flowerpainting": 436870,
        "#dailypainting": 420073,
        "#acrylicpaintings": 370207,
        "#minipainting": 368443
    },
    "Pastry Shop":{
        "#pastryclass": 54675,
        "#pastrycook": 54494,
        "#bakingandpastry": 51512,
        "#homemadepastry": 49970,
        "#danishpastry": 49675,
        "#chefpastry": 46729
    },
    "Phone Repairs":{
        "#phonerepair":1
    },
    "Pizzeria":{
        "#dailypizza": 316970,
        "#pizzaitaliana": 307232,
        "#pizzagate": 302903,
        "#italianpizza": 300020,
        "#nationalpizzaday": 251146,
        "#pepperonipizza": 224795,
        "#pizzasisters4lyfe": 193740,
        "#pizzapie": 185967,
        "#pizzaslice": 184715
    },
    "Plumbing":{
        "#plumbingdesign": 5013,
        "#plumbingapprentice": 4573,
        "#plumbingsupplies": 4168,
        "#loveplumbing": 4110,
        "#roofplumbing": 3948,
        "#plumbingpro": 3743,
        "#plumbinginstallations": 3485,
        "#plumbingcompanies": 3183
    },
    "Printing":{
        "#scarfprinting": 120365,
        "#tasprinting": 108808,
        "#maxiprinting": 105850,
        "#watertransferprinting": 104850,
        "#printingservices": 97141,
        "#largeformatprinting": 96122
    },
    "Radio":{
        "#hiphopradio": 160612,
        "#liveradio": 147849,
        "#instaradio": 146348,
        "#radiodeejay": 143969,
        "#tuneinradio": 139988,
        "#radios": 137422,
        "#radiofm": 134905,
        "#collegeradio": 132776
    },
    "Real Estate":{
        "#futurehouse": 1262290,
        "#homeinterior": 3464341,
        "#homeinspiration": 3517643,
        "#incomeproperty": 89196,
        "#localrealtor": 81481,
        "#propertysales": 100751,
        "#propertyinvesting": 91520,
        "#realestateinvestor": 1971384,
        "#realtors": 1990964
    },
    "Resort":{
        "#resort": 7335651,
        "#resortcollection": 73595,
        "#travel": 492251333,
        "#vacation": 117463109,
        "#summer": 450939349
    },
    "Roofing":{
        "#roofingspecialists": 5431,
        "#roofingsystems": 5287,
        "#roofingmaterials": 5128,
        "#roofingsheets": 5047,
        "#roofingcrew": 5015
    },
    "Sanitation":{
        "#sanitationmatters": 334,
        "#hygieneandsanitation": 311,
        "#sanitationisdignity": 256,
        "#servicesanitation": 252,
        "#deptofsanitation": 250
    },
    "Self Storage":{
        "#selfstorage": 126797,
        "#unlimitedselfstorage": 108,
        "#selfstorageconversion": 65,
        "#selfstoragetech": 55
    },
    "Sporting Event":{
        "#sportingevent": 9292
    },
    "Steak House":{
        "#cheesesteaks": 73700,
        "#filletsteak": 67578,
        "#steakandpotatoes": 66116,
        "#steaksalad": 65396,
        "#chickenfriedsteak": 64804,
        "#steaktime": 64683,
        "#hangersteak": 60553
    },
    "Towing":{
        "#towing": 432660,
        "#towingbar": 4476,
        "#cartowing": 4403,
        "#viptowing": 4361,
        "#freetowing": 4067,
        "#jasatowingmobil": 3981,
        "#jetstowing": 3826,
        "#flatbedtowing": 3797,
        "#towingsolo": 3736
    },
    "Warehousing":{
        "#warehouse": 1341461,
        "#warehousing": 66595
    }
}
